[
    {
        "label": 1,
        "lat": 33.64331,
        "lon":-84.43274,
        "name":"C52",
        "neighbors": [2,3]
    },
    {
        "label": 2,
        "lat": 33.64331,
        "lon":-84.43252,
        "name":"C55",
        "neighbors": [1,5]
    },
    {
        "label": 3,
        "lat": 33.64329,
        "lon":-84.43284,
        "name":"C50",
        "neighbors": [1,4]
    },
    {
        "label": 4,
        "lat": 33.64310,
        "lon":-84.43282,
        "name":"C46",
        "neighbors": [3,6]
    },
    {
        "label": 5,
        "lat": 33.64311,
        "lon":-84.43241,
        "name":"C49",
        "neighbors": [6,2]
    },
    {
        "label": 6,
        "lat": 33.64311,
        "lon":-84.43262,
        "name":"inter",
        "neighbors": [4,5,7]
    },
    {
        "label": 7,
        "lat": 33.64298,
        "lon":-84.43262,
        "name":"inter",
        "neighbors": [6,8]
    },
    {
        "label": 8,
        "lat": 33.64298,
        "lon":-84.43246,
        "name":"C47",
        "neighbors": [7]
    },
    {
        "label": 9,
        "lat": 33.64287,
        "lon":-84.43262,
        "name":"inter",
        "neighbors": [7,10,11,12]
    },
    {
        "label": 10,
        "lat": 33.64287,
        "lon":-84.43272,
        "name":"Sweet Georgia's",
        "neighbors": [9]
    },
    {
        "label": 11,
        "lat": 33.64287,
        "lon":-84.43255,
        "name":"Washroom",
        "neighbors": [9]
    },
    {
        "label": 12,
        "lat": 33.64274843143577,
        "lon": -84.43262077839184,
        "name":"inter",
        "neighbors": [9,13,14]
    },
    {
        "label": 13,
        "lat": 33.6427311709908,
        "lon": -84.43279940170908,
        "name":"C42",
        "neighbors": [12]
    },
    {
        "label": 14,
        "lat": 33.642695594600134, 
        "lon": -84.4326219372323,
        "name":"inter",
        "neighbors": [12,15,16]
    },
    {
        "label": 15,
        "lat": 33.64269057043522, 
        "lon": -84.4325656108421,
        "name":"Midtown Magazines",
        "neighbors": [14]
    },
    {
        "label": 16,
        "lat": 33.64245722556394, 
        "lon":-84.43260651453022,
        "name":"inter",
        "neighbors": [14,17,18]
    },
    {
        "label": 17,
        "lat": 33.64244996841665,
        "lon": -84.43246100468889,
        "name":"C43", 
        "neighbors": [16]
    },
    {
        "label": 18,
        "lat": 33.642284320846585, 
        "lon":-84.43261986896624,
        "name":"inter",
        "neighbors": [16,19,21,20]
    },
    {
        "label": 19,
        "lat":33.642277433416716, 
        "lon":-84.43278533023997,
        "name":"C40",
        "neighbors": [18]
    },
    {
        "label": 20,
        "lat":33.642266241341986, 
        "lon":-84.43245337355957,
        "name":"C41",
        "neighbors": [18]
    },
    {
        "label": 21,
        "lat":33.64219650607434,
        "lon": -84.4326291761629,
        "name":"inter",
        "neighbors": [18,22]
    },
    {
        "label": 22,
        "lat":33.64183921954994,
        "lon":-84.43263124442873,
        "name":"inter",
        "neighbors": [23,21,24]
    },
    {
        "label": 23,
        "lat":33.64183749768361,
        "lon": -84.43277809130919,
        "name":"C36",
        "neighbors": [22]
    },
    {
        "label": 24,
        "lat":33.641767762068724,
        "lon": -84.43260952763657,
        "name":"inter",
        "neighbors": [22,25,26,27]
    },
    {
        "label": 25,
        "lat":33.64176604020097, 
        "lon":-84.4324637148891,
        "name":"C37",
        "neighbors": [24]
    },
    {
        "label": 26,
        "lat":33.641604184475554,
        "lon": -84.43278119370821,
        "name":"C34",
        "neighbors": [24]
    },
    {
        "label": 27,
        "lat":33.64134848624748,
        "lon": -84.43263434682761,
        "name":"inter",
        "neighbors": [28,29,24,30]
    },
    {
        "label": 28,
        "lat":33.64135623468966,
        "lon": -84.43277085237844,
        "name":"C30",
        "neighbors": [27]
    },
    {
        "label": 29,
        "lat":33.64138378470064,
        "lon": -84.43245957835725,
        "name":"C35",
        "neighbors": [27]
    },
    {
        "label": 30,
        "lat":33.64113927803508,
        "lon": -84.43261573243493,
        "name":"inter",
        "neighbors": [27,31,32]
    },
    {
        "label": 31,
        "lat":33.64114099991537,
        "lon": -84.43245544182601,
        "name":"C33",
        "neighbors": [30]
    },
    {
        "label": 32,
        "lat":33.64064958532581,
        "lon": -84.43262981641084,
        "name":"inter",
        "neighbors": [30,33,34]
    },
    {
        "label": 33,
        "lat":33.6406926325674,
        "lon": -84.432783902222,
        "name":"C22",
        "neighbors": [32]
    },
    {
        "label": 34,
        "lat":33.64034594012737,
        "lon": -84.4326097399991,
        "name":"inter",
        "neighbors": [32,37,35,36]
    },
    {
        "label": 35,
        "lat":33.640336317550904,
        "lon": -84.43278953445252,
        "name":"C20",
        "neighbors": [34]
    },
    {
        "label": 36,
        "lat":33.64034487095226,
        "lon": -84.43244535649879,
        "name":"C21",
        "neighbors": [34]
    },
    {
        "label": 37,
        "lat":33.639921476556694,
        "lon": -84.4326123084914,
        "name":"inter",
        "neighbors": [34,38,39,40]
    },
    {
        "label": 38,
        "lat":33.63993751426081,
        "lon": -84.43277540774562,
        "name":"C16",
        "neighbors": [37]
    },
    {
        "label": 39,
        "lat":33.63986908670249,
        "lon": -84.43245177772941,
        "name":"C17",
        "neighbors": [37]
    },
    {
        "label": 40,
        "lat":33.63962531307529,
        "lon": -84.43258919206137,
        "name":"inter",
        "neighbors": [37,41,43,42,44]
    },
    {
        "label": 41,
        "lat":33.63962852062738,
        "lon": -84.43277797623749,
        "name":"C14",
        "neighbors": [40]
    },
    {
        "label": 42,
        "lat":33.639577629244855,
        "lon": -84.43264904159565,
        "name":"Jersey' Mike's",
        "neighbors": [40]
    },
    {
        "label": 43,
        "lat":33.63953229401269,
        "lon": -84.432450493483,
        "name":"C15",
        "neighbors": [40]
    },
    {
        "label": 44,
        "lat":33.639333425328104,
        "lon": -84.43258405507775,
        "name":"inter",
        "neighbors": [40,45,46]
    },
    {
        "label": 45,
        "lat":33.63933128695272,
        "lon": -84.43245434622204,
        "name":"C13",
        "neighbors": [44]
    },
    {
        "label": 46,
        "lat":33.63906826637657,
        "lon": -84.43261359273797,
        "name":"inter",
        "neighbors": [44,48,47]
    },
    {
        "label": 47,
        "lat":33.63915593999122,
        "lon": -84.43278825020703,
        "name":"C12",
        "neighbors": [46]
    },
    {
        "label": 48,
        "lat":33.63881593693061,
        "lon": -84.43260203452351,
        "name":"inter",
        "neighbors": [46,49,50,51]
    },
    {
        "label": 49,
        "lat":33.638817006124704,
        "lon": -84.43276384953161,
        "name":"C10",
        "neighbors": [48]
    },
    {
        "label": 50,
        "lat":33.63878813787952,
        "lon": -84.43246205169905,
        "name":"C9",
        "neighbors": [48]
    },
    {
        "label": 51,
        "lat":33.638438510580905, 
        "lon":-84.43261616123115,
        "name":"inter",
        "neighbors": [48,52,53,54]
    },
    {
        "label": 52,
        "lat":33.63844064897845,
        "lon": -84.43277027076267,
        "name":"C6",
        "neighbors": [51]
    },
    {
        "label": 53,
        "lat":33.638453479362624,
        "lon": -84.43244920923865,
        "name":"C7",
        "neighbors": [51]
    },
    {
        "label": 54,
        "lat":33.63810491990636,
        "lon": -84.43259561329364,
        "name":"inter",
        "neighbors": [51,55,56,57]
    },
    {
        "label": 55,
        "lat":33.63811026592084,
        "lon": -84.4327702707627,
        "name":"C4",
        "neighbors": [54]
    },
    {
        "label": 56,
        "lat":33.638092089470256,
        "lon": -84.43244150376212,
        "name":"C5",
        "neighbors": [54]
    },
    {
        "label": 57,
        "lat":33.63783244926734,
        "lon": -84.43260710927979,
        "name":"inter",
        "neighbors": [54,58,59,60]
    },
    {
        "label": 58,
        "lat":33.63783314256185,
        "lon": -84.43244389408854,
        "name":"C3",
        "neighbors": [57]
    },
    {
        "label": 59,
        "lat":333.637749947180126,
        "lon": -84.43250218522826,
        "name":"C1",
        "neighbors": [57]
    },
    {
        "label": 60,
        "lat":33.637749947180126,
        "lon": -84.4327278552121,
        "name":"C2",
        "neighbors": [57]
    }
]